{
  "AccelLinks": "",
  "AdesPhantom": "刺客三觉",
  "AerialJump": "空跃",
  "Amateras": "天照",
  "Amateras_VP1": "天照",
  "Amateras_VP2": "天照",
  "AmbitionOfBallacre": "巴拉克的野心",
  "AmbitionOfBallacre_VP1": "巴拉克的野心_VP1",
  "AmbitionOfBallacre_VP2": "巴拉克的野心_VP2",
  "AnkleCut": "扫堂枪",
  "ApportBallacre": "",
  "ApportBallacre_VP1": "",
  "ApportBallacre_VP2": "",
  "AssasinsAttitude": "潜行信条",
  "Assassination": "瞬杀an立绘",
  "Assassination_VP1": "瞬杀an立绘_VP1",
  "Assassination_VP2": "瞬杀an立绘_VP2",
  "BackStep": "",
  "BallacreAdvent": "",
  "BallacreStrongAttack": "",
  "BigKunai": "火遁：螺旋手里剑",
  "BladeGust": "刃舞",
  "BladeGust_VP1": "刃舞_VP1",
  "BladeGust_VP2": "刃舞_VP2",
  "BlameOfDead": "死灵之怨",
  "BlameOfDeadEx": "死灵之缚",
  "BlameOfDeadEx_VP1": "死灵之缚_VP1",
  "BlameOfDeadEx_VP2": "死灵之缚_VP2",
  "BoneShield": "骨盾",
  "BreakingRush": "疾驰",
  "Cardioclasis": "穿心",
  "ChainReaction": "幽冥链狱：索命",
  "ChainSaw": "旋刃",
  "ChainSawEx": "陨落螺旋刺",
  "ChainSawEx_VP1": "陨落螺旋刺_VP1",
  "ChainSawEx_VP2": "陨落螺旋刺_VP2",
  "CoconOfUndead": "亡者之茧",
  "CovertAction": "潜影刺击",
  "CovertAction_VP1": "潜影刺击",
  "CovertAction_VP2": "潜影刺击",
  "CurseSpear": "诅咒之箭",
  "CuttingNeck": "割喉",
  "DanceOfGrimReaper": "死亡连舞",
  "DanceOfGrimReaper_VP1": "死亡连舞_VP1",
  "DanceOfGrimReaper_VP2": "死亡连舞_VP2",
  "DarkLure": "百鬼夜行",
  "DarkNail": "死亡之爪",
  "DarkRitual": "暗黑仪式",
  "DarkSoul": "暗魂波",
  "DeathHurricane": "死亡风暴",
  "DeathHurricane_VP1": "死亡风暴",
  "DeathHurricane_VP2": "死亡风暴",
  "DeitiesRebirth": "忍法：六道轮回",
  "Distribution": "月影突袭",
  "Distribution_VP1": "月影突袭",
  "Distribution_VP2": "月影突袭",
  "DivingArrow": "疾空踏",
  "DoomField": "",
  "DoublePierce": "双刃穿刺",
  "Eraser": "天诛",
  "ExcelStrike": "绝境瞬狱袭",
  "ExcelStrike_VP1": "绝境瞬狱袭",
  "ExcelStrike_VP2": "绝境瞬狱袭",
  "ExecutionerSlash": "暴君湮灭斩",
  "ExecutionerSlash_VP1": "暴君湮灭斩",
  "ExecutionerSlash_VP2": "暴君湮灭斩",
  "ExoticRampant": "乱空杀",
  "ExoticRampant_VP1": "乱空杀",
  "ExoticRampant_VP2": "乱空杀",
  "ExtractHeart": "剜心",
  "ExtractHeart_VP1": "剜心_VP1",
  "ExtractHeart_VP2": "剜心_VP2",
  "FinalDestruction": "影戮",
  "FinalDestruction_VP1": "影戮_VP1",
  "FinalDestruction_VP2": "影戮_VP2",
  "FireHide": "火遁：红莲",
  "FireMark": "毕方之印",
  "FlameBall": "火遁：豪火球之术",
  "FlameCut": "焰刃",
  "FlameFlower": "火遁：炎璇天舞",
  "FlameFlower_VP1": "火遁：炎璇天舞_VP1",
  "FlameFlower_VP2": "火遁：炎璇天舞_VP2",
  "FlameTornado": "火遁：飓风煞",
  "FlyingSquirrel": "忍法：飞鼠",
  "FlyingSwallow": "",
  "FlyingSwallow_VP1": "",
  "FlyingSwallow_VP2": "",
  "FuumaShuriken": "",
  "FuumaShuriken_VP1": "",
  "FuumaShuriken_VP2": "",
  "GasolineFire": "火遁：蟾蜍油炎弹",
  "GasolineFire_VP1": "火遁：蟾蜍油炎弹_VP1",
  "GasolineFire_VP2": "火遁：蟾蜍油炎弹_VP2",
  "GotoHell": "追命",
  "GrabCollar": "",
  "Guillotine": "巴拉克的愤怒",
  "Guillotine_VP1": "巴拉克的愤怒_VP1",
  "Guillotine_VP2": "巴拉克的愤怒_VP2",
  "HatefulGhost": "",
  "HatefulGhost_VP1": "",
  "HatefulGhost_VP2": "",
  "HitEnd": "终结之击",
  "HoldUp": "夺魂",
  "HorrorOfMoros": "",
  "Hurricane": "剑刃风暴",
  "IlusionShuriken": "幻影手里剑",
  "JadeKamaitachi": "",
  "JumpPowerUp": "",
  "LeaveTrace": "",
  "LightningArrow": "雷光刃影",
  "LightningArrow_VP1": "雷光刃影",
  "LightningArrow_VP2": "雷光刃影",
  "LivingDead": "降临 : 莱迪娅",
  "LivingDead_VP1": "降临 : 莱迪娅",
  "LivingDead_VP2": "降临 : 莱迪娅",
  "MadnessBallacre": "",
  "MagicalAttackUp": "",
  "MenacingSeize": "",
  "Migawari": "忍法：替身术",
  "Migawari_VP1": "忍法：替身术_VP1",
  "Migawari_VP2": "忍法：替身术_VP2",
  "NicolasBehavior": "",
  "NicolasBlackArachnia": "",
  "NicolasBlackArachnia_VP1": "",
  "NicolasBlackArachnia_VP2": "",
  "NicolasBlackArea": "",
  "NicolasBlackWave": "",
  "NicolasBlackWaveEx": "",
  "NicolasBlackWave_VP1": "",
  "NicolasBlackWave_VP2": "",
  "NicolasSummonZombie": "",
  "NovaRemnant": "天渊星狱",
  "Phantomstrom": "千魂祭",
  "QuickStanding": "",
  "RisingCut": "翔击",
  "ShadowCut": "影袭",
  "ShadowDancing": "潜行领域",
  "ShadowFake": "",
  "Shadowless": "影舞三觉",
  "ShadowMove": "",
  "ShadowPierce": "绝命飞刃",
  "ShadowPierce_VP1": "绝命飞刃_VP1",
  "ShadowPierce_VP2": "绝命飞刃_VP2",
  "ShadowSting": "八荒影杀",
  "ShadowSting_VP1": "八荒影杀",
  "ShadowSting_VP2": "八荒影杀",
  "ShakeDown": "暗掠",
  "ShiningCut": "弧光闪",
  "ShiningCutAerial": "",
  "Shuriken": "",
  "SideStep": "侧步",
  "SilverStream": "月轮舞",
  "SkinTakeOff": "忍法：影分身",
  "SkyRoads": "火遁：炎天道",
  "SkyRoads_VP1": "火遁：炎天道_VP1",
  "SkyRoads_VP2": "火遁：炎天道_VP2",
  "Slicer": "切割",
  "SonicAssault": "疾风乱舞",
  "SonicAssault_VP1": "疾风乱舞_VP1",
  "SonicAssault_VP2": "疾风乱舞_VP2",
  "StreamCloser": "月舞终结",
  "SummonNicolas": "",
  "SuperArmorOnCast": "",
  "SwordDance": "旋舞斩",
  "SwordOfKusanagi": "火炎灼空 : 草雉剑",
  "VanditCut": "绝心击",
  "VanishingIllusion": "幻灭瞬杀",
  "VerticalSpiral": "螺旋穿刺",
  "VerticalSpiralEx": "旋刃冲击",
  "VerticalSpiralEx_VP1": "旋刃冲击_VP1",
  "VerticalSpiralEx_VP2": "旋刃冲击_VP2",
  "VerticalSpiral_VP1": "螺旋穿刺_VP1",
  "VerticalSpiral_VP2": "螺旋穿刺_VP2",
  "WoodMove": "",
  "YamataOrochi": "八岐大蛇",
  "YamataOrochi_VP1": "八岐大蛇",
  "YamataOrochi_VP2": "八岐大蛇",
  "Yatagarasu": "忍者三觉",
  "Zetsuei": "影斩：乱舞"
}